dislord/__init__.py
dislord/api.py
dislord/client.py
dislord/error.py
dislord/server.py
dislord/models/__init__.py
dislord/models/api.py
dislord/models/application.py
dislord/models/base.py
dislord/models/channel.py
dislord/models/command.py
dislord/models/guild.py
dislord/models/interaction.py
dislord/models/locale.py
dislord/models/type.py
dislord/models/user.py
examples/hello.py
examples/options.py
examples/simple.py
examples/sync.py
dislord-0.0.1.post23.dist-info/LICENSE
dislord-0.0.1.post23.dist-info/METADATA
dislord-0.0.1.post23.dist-info/WHEEL
dislord-0.0.1.post23.dist-info/top_level.txt
dislord-0.0.1.post23.dist-info/RECORD
