Metadata-Version: 2.1
Name: dislord
Version: 0.0.1.post23
Summary: A serverless optimized discord API library using interactions.
Author-email: Jack Draper <drapj002@gmail.com>
Project-URL: Homepage, https://github.com/JayDwee/dislord
Project-URL: Bug Tracker, https://github.com/JayDwee/dislord/issues
Classifier: Programming Language :: Python :: 3
Classifier: License :: OSI Approved :: MIT License
Classifier: Operating System :: OS Independent
Requires-Python: >=3.11
License-File: LICENSE
Requires-Dist: discord-interactions ~=0.4.0
Requires-Dist: requests ~=2.31.0
